CITIfile.py
CITIfile-0.1.6.dist-info/LICENSE
CITIfile-0.1.6.dist-info/METADATA
CITIfile-0.1.6.dist-info/WHEEL
CITIfile-0.1.6.dist-info/top_level.txt
CITIfile-0.1.6.dist-info/RECORD
