Metadata-Version: 2.1
Name: CITIfile
Version: 0.1.6
Summary: To parse CITI format file to xarray.
Home-page: https://github.com/TitorX/CITIfile
Author: Titor
Author-email: titor.sun@gmail.com
Classifier: License :: OSI Approved :: MIT License
Classifier: Programming Language :: Python :: 3
License-File: LICENSE
Requires-Dist: xarray>=0.14.1
